src/CheckerSrtFormat.py
src/Controller.py
src/DialogScript.py
src/ErrorClass.py
src/GuiPyConcatSRT.py
src/ReaderFileSrt.py
src/WriterFileSrt.py
src/__init__.py
src/run_cli.py
src/run_gui.py
pyconcatsrt-0.1.3.dist-info/LICENSE
pyconcatsrt-0.1.3.dist-info/METADATA
pyconcatsrt-0.1.3.dist-info/WHEEL
pyconcatsrt-0.1.3.dist-info/entry_points.txt
pyconcatsrt-0.1.3.dist-info/RECORD
